{
  "shopify_gb_14857941221760_52570110886272": {
    "product_id": "shopify_gb_14857941221760_52570110886272",
    "product_title": "Hard Wax Oil For Wood | Long Lasting Wood Protection 1 Litre",
    "clicks": 2,
    "impressions": 208,
    "revenue": 0.0,
    "cost": 0.28
  },
  "shopify_gb_14857945678208_52570140017024": {
    "product_id": "shopify_gb_14857945678208_52570140017024",
    "product_title": "Raw Linseed Oil For Wood 500ml | 100% Pure & Natural | Food-Safe Wood Oil | Grain Guard",
    "clicks": 0,
    "impressions": 145,
    "revenue": 0.0,
    "cost": 0.0
  },
  "shopify_gb_14857945678208_52570140049792": {
    "product_id": "shopify_gb_14857945678208_52570140049792",
    "product_title": "Raw Linseed Oil For Wood 1 Litre | 100% Pure & Natural | Food-Safe",
    "clicks": 1,
    "impressions": 152,
    "revenue": 0.0,
    "cost": 0.5
  },
  "shopify_gb_8784875847954_47734950723858": {
    "product_id": "shopify_gb_8784875847954_47734950723858",
    "product_title": "Grain Guard Wood Stain 500ml - Black Ebony - Water-Based, Quick Drying, 12m\u00b2/Litre - Interior/Exterior",
    "clicks": 2,
    "impressions": 103,
    "revenue": 12.99,
    "cost": 2.42
  },
  "shopify_gb_8784875847954_47734950756626": {
    "product_id": "shopify_gb_8784875847954_47734950756626",
    "product_title": "Wood Stain | Water Based | 1 Litre - Black Ebony",
    "clicks": 1,
    "impressions": 70,
    "revenue": 0.0,
    "cost": 0.67
  },
  "shopify_gb_8784875847954_47734950789394": {
    "product_id": "shopify_gb_8784875847954_47734950789394",
    "product_title": "Grain Guard Wood Stain 5 Litre - Black Ebony Water Based Interior/Exterior Wood Stain, Quick Dry, Long Lasting, 12m\u00b2 Coverage",
    "clicks": 1,
    "impressions": 24,
    "revenue": 0.0,
    "cost": 1.18
  },
  "shopify_gb_8784875847954_47734950822162": {
    "product_id": "shopify_gb_8784875847954_47734950822162",
    "product_title": "Wood Stain | Water Based | 500ml - Dark Red Mahogany",
    "clicks": 0,
    "impressions": 41,
    "revenue": 0.0,
    "cost": 0.0
  },
  "shopify_gb_8784875847954_47734950854930": {
    "product_id": "shopify_gb_8784875847954_47734950854930",
    "product_title": "Wood Stain | Water Based | 1 Litre - Dark Red Mahogany",
    "clicks": 0,
    "impressions": 6,
    "revenue": 0.0,
    "cost": 0.0
  },
  "shopify_gb_8784875847954_47734950887698": {
    "product_id": "shopify_gb_8784875847954_47734950887698",
    "product_title": "Wood Stain | Water Based | 5 Litre - Dark Red Mahogany",
    "clicks": 0,
    "impressions": 7,
    "revenue": 0.0,
    "cost": 0.0
  },
  "shopify_gb_8784875847954_47734950953234": {
    "product_id": "shopify_gb_8784875847954_47734950953234",
    "product_title": "Wood Stain | Water Based | 1 Litre - Dark Walnut",
    "clicks": 2,
    "impressions": 174,
    "revenue": 0.0,
    "cost": 2.46
  },
  "shopify_gb_8784875847954_47734950986002": {
    "product_id": "shopify_gb_8784875847954_47734950986002",
    "product_title": "Grain Guard Wood Stain 5 Litre - Dark Walnut, Water Based, Quick Drying, Long Lasting, 12m\u00b2 Coverage, Interior/Exterior Use, Eco-Friendly",
    "clicks": 0,
    "impressions": 37,
    "revenue": 0.0,
    "cost": 0.0
  },
  "shopify_gb_8784875847954_47734951018770": {
    "product_id": "shopify_gb_8784875847954_47734951018770",
    "product_title": "Grain Guard Wood Stain 500ml English Oak - Water Based, Quick Drying, Long Lasting, 12m\u00b2 Coverage, Interior/Exterior Use",
    "clicks": 0,
    "impressions": 33,
    "revenue": 0.0,
    "cost": 0.0
  },
  "shopify_gb_8784875847954_47734951051538": {
    "product_id": "shopify_gb_8784875847954_47734951051538",
    "product_title": "Wood Stain | Water Based | 1 Litre - English Oak",
    "clicks": 0,
    "impressions": 58,
    "revenue": 0.0,
    "cost": 0.0
  },
  "shopify_gb_8784875847954_47734951084306": {
    "product_id": "shopify_gb_8784875847954_47734951084306",
    "product_title": "Water Based Wood Stain - 5 Litre - English Oak",
    "clicks": 0,
    "impressions": 15,
    "revenue": 0.0,
    "cost": 0.0
  },
  "shopify_gb_8784875847954_47734951117074": {
    "product_id": "shopify_gb_8784875847954_47734951117074",
    "product_title": "Light Oak Wood Stain Water Based - 500ml | Grain Guard",
    "clicks": 1,
    "impressions": 44,
    "revenue": 0.0,
    "cost": 1.42
  },
  "shopify_gb_8784875847954_47734951149842": {
    "product_id": "shopify_gb_8784875847954_47734951149842",
    "product_title": "Grain Guard Wood Stain 1L - Light Oak - Quick Dry, Water Based, Interior/Exterior 12m\u00b2/Litre",
    "clicks": 0,
    "impressions": 1,
    "revenue": 0.0,
    "cost": 0.0
  },
  "shopify_gb_8784875847954_47734951182610": {
    "product_id": "shopify_gb_8784875847954_47734951182610",
    "product_title": "Wood Stain | Water Based | 5 Litre - Light Oak",
    "clicks": 0,
    "impressions": 14,
    "revenue": 0.0,
    "cost": 0.0
  },
  "shopify_gb_8784875847954_47734951215378": {
    "product_id": "shopify_gb_8784875847954_47734951215378",
    "product_title": "Wood Stain | Water Based | 500ml - Medium Oak",
    "clicks": 0,
    "impressions": 65,
    "revenue": 0.0,
    "cost": 0.0
  },
  "shopify_gb_8784875847954_47734951248146": {
    "product_id": "shopify_gb_8784875847954_47734951248146",
    "product_title": "Wood Stain | Water Based | 1 Litre - Medium Oak",
    "clicks": 0,
    "impressions": 42,
    "revenue": 0.0,
    "cost": 0.0
  },
  "shopify_gb_8784875847954_47734951280914": {
    "product_id": "shopify_gb_8784875847954_47734951280914",
    "product_title": "Grain Guard Wood Stain, Water Based, 5 Litre - Medium Oak, Quick Dry, Long Lasting, 12m\u00b2 Coverage, Interior/Exterior, Environmentally Friendly",
    "clicks": 0,
    "impressions": 28,
    "revenue": 0.0,
    "cost": 0.0
  },
  "shopify_gb_8784875847954_48957267804434": {
    "product_id": "shopify_gb_8784875847954_48957267804434",
    "product_title": "Grain Guard Wood Stain 500ml - Golden Oak - Water Based, Quick Drying, Long Lasting, Interior/Exterior, 12m\u00b2/Litre",
    "clicks": 0,
    "impressions": 38,
    "revenue": 0.0,
    "cost": 0.0
  },
  "shopify_gb_8784875847954_48957267837202": {
    "product_id": "shopify_gb_8784875847954_48957267837202",
    "product_title": "Wood Stain | Water Based | 1 Litre - Golden Oak",
    "clicks": 0,
    "impressions": 11,
    "revenue": 0.0,
    "cost": 0.0
  },
  "shopify_gb_8784875847954_48957267869970": {
    "product_id": "shopify_gb_8784875847954_48957267869970",
    "product_title": "Wood Stain | Water Based | 5 Litre - Golden Oak",
    "clicks": 0,
    "impressions": 15,
    "revenue": 0.0,
    "cost": 0.0
  },
  "shopify_gb_8784875847954_48957267902738": {
    "product_id": "shopify_gb_8784875847954_48957267902738",
    "product_title": "Grain Guard Wood Stain 500ml - Antique Stripped Pine - Water-Based, Quick Drying, Long Lasting, 12m\u00b2 Coverage. 500ml",
    "clicks": 1,
    "impressions": 29,
    "revenue": 0.0,
    "cost": 0.39
  },
  "shopify_gb_8784875847954_48957267935506": {
    "product_id": "shopify_gb_8784875847954_48957267935506",
    "product_title": "Wood Stain | Water Based | 1 Litre - Antique Stripped Pine",
    "clicks": 0,
    "impressions": 6,
    "revenue": 0.0,
    "cost": 0.0
  },
  "shopify_gb_8784875847954_48957267968274": {
    "product_id": "shopify_gb_8784875847954_48957267968274",
    "product_title": "Wood Stain | Water Based | 5 Litre - Antique Stripped Pine",
    "clicks": 0,
    "impressions": 7,
    "revenue": 0.0,
    "cost": 0.0
  },
  "shopify_gb_8784875847954_48957268001042": {
    "product_id": "shopify_gb_8784875847954_48957268001042",
    "product_title": "Grain Guard Wood Stain 500ml - Very Red Mahogany - Water Based, Quick Drying, Long Lasting, Interior/Exterior Use, 12m\u00b2 Coverage",
    "clicks": 0,
    "impressions": 18,
    "revenue": 0.0,
    "cost": 0.0
  },
  "shopify_gb_8784875847954_48957268033810": {
    "product_id": "shopify_gb_8784875847954_48957268033810",
    "product_title": "Grain Guard Water Based Wood Stain - 1 Litre - Very Red Mahogany - Quick Drying, Long Lasting, 12m\u00b2 Coverage - Interior/Exterior Use",
    "clicks": 0,
    "impressions": 1,
    "revenue": 0.0,
    "cost": 0.0
  },
  "shopify_gb_8784875847954_48957268066578": {
    "product_id": "shopify_gb_8784875847954_48957268066578",
    "product_title": "Wood Stain | Water Based | 5 Litre - Very Red Mahogany",
    "clicks": 0,
    "impressions": 4,
    "revenue": 0.0,
    "cost": 0.0
  },
  "shopify_gb_8784875847954_48957268099346": {
    "product_id": "shopify_gb_8784875847954_48957268099346",
    "product_title": "Wood Stain | Water Based | 500ml - Brown Mahogany",
    "clicks": 0,
    "impressions": 9,
    "revenue": 0.0,
    "cost": 0.0
  },
  "shopify_gb_8784875847954_48957268132114": {
    "product_id": "shopify_gb_8784875847954_48957268132114",
    "product_title": "Wtare Based Wood Stain | 1 Litre - Brown Mahogany",
    "clicks": 0,
    "impressions": 6,
    "revenue": 0.0,
    "cost": 0.0
  },
  "shopify_gb_8784875847954_48957268164882": {
    "product_id": "shopify_gb_8784875847954_48957268164882",
    "product_title": "Wood Stain | Water Based | 5 Litre - Brown Mahogany",
    "clicks": 0,
    "impressions": 3,
    "revenue": 0.0,
    "cost": 0.0
  },
  "shopify_gb_8784875847954_48957268197650": {
    "product_id": "shopify_gb_8784875847954_48957268197650",
    "product_title": "Wood Stain | Water Based | 500ml - French Oak",
    "clicks": 0,
    "impressions": 18,
    "revenue": 0.0,
    "cost": 0.0
  },
  "shopify_gb_8784875847954_48957268230418": {
    "product_id": "shopify_gb_8784875847954_48957268230418",
    "product_title": "Wood Stain | Water Based | 1 Litre - French Oak",
    "clicks": 0,
    "impressions": 58,
    "revenue": 0.0,
    "cost": 0.0
  },
  "shopify_gb_8784875847954_48957268263186": {
    "product_id": "shopify_gb_8784875847954_48957268263186",
    "product_title": "Wood Stain | Water Based | 5 Litre - French Oak",
    "clicks": 0,
    "impressions": 18,
    "revenue": 0.0,
    "cost": 0.0
  },
  "shopify_gb_8784875847954_48957268295954": {
    "product_id": "shopify_gb_8784875847954_48957268295954",
    "product_title": "Wood Stain | Water Based | 500ml - Golden Pine",
    "clicks": 0,
    "impressions": 13,
    "revenue": 0.0,
    "cost": 0.0
  },
  "shopify_gb_8784875847954_48957268328722": {
    "product_id": "shopify_gb_8784875847954_48957268328722",
    "product_title": "Water Based Wood Stain |- 1 Litre - Golden Pine",
    "clicks": 0,
    "impressions": 4,
    "revenue": 0.0,
    "cost": 0.0
  },
  "shopify_gb_8784875847954_48957268361490": {
    "product_id": "shopify_gb_8784875847954_48957268361490",
    "product_title": "Wood Stain | Water Based | 5 Litre - Golden Pine",
    "clicks": 0,
    "impressions": 4,
    "revenue": 0.0,
    "cost": 0.0
  },
  "shopify_gb_8784875847954_48957268394258": {
    "product_id": "shopify_gb_8784875847954_48957268394258",
    "product_title": "GrainGuard Wood Stain 500ml Dark Pine - Water-Based, Quick Drying, Long Lasting, Interior/Exterior, 12m\u00b2/Litre Coverage",
    "clicks": 0,
    "impressions": 1,
    "revenue": 0.0,
    "cost": 0.0
  },
  "shopify_gb_8784875847954_48957268427026": {
    "product_id": "shopify_gb_8784875847954_48957268427026",
    "product_title": "Wood Stain | Water Based | 1 Litre - Dark Pine",
    "clicks": 0,
    "impressions": 4,
    "revenue": 0.0,
    "cost": 0.0
  },
  "shopify_gb_8784875847954_48957268459794": {
    "product_id": "shopify_gb_8784875847954_48957268459794",
    "product_title": "Wood Stain | Water Based | 5 Litre - Dark Pine",
    "clicks": 0,
    "impressions": 5,
    "revenue": 0.0,
    "cost": 0.0
  },
  "shopify_gb_8784875847954_48957268492562": {
    "product_id": "shopify_gb_8784875847954_48957268492562",
    "product_title": "Wood Stain | Water Based | 500ml - Light Rosewood",
    "clicks": 0,
    "impressions": 9,
    "revenue": 0.0,
    "cost": 0.0
  },
  "shopify_gb_8784875847954_48957268525330": {
    "product_id": "shopify_gb_8784875847954_48957268525330",
    "product_title": "Wood Stain | Water Based | 1 Litre - Light Rosewood",
    "clicks": 0,
    "impressions": 5,
    "revenue": 0.0,
    "cost": 0.0
  },
  "shopify_gb_8784875847954_48957268558098": {
    "product_id": "shopify_gb_8784875847954_48957268558098",
    "product_title": "Wood Stain Water Based - 5 Litre - Light Rosewood",
    "clicks": 0,
    "impressions": 4,
    "revenue": 0.0,
    "cost": 0.0
  },
  "shopify_gb_8784876241170_47735016947986": {
    "product_id": "shopify_gb_8784876241170_47735016947986",
    "product_title": "Grain Guard Clear Wax Polish 600ml: Natural Beeswax & Carnauba Polish, Non-Toxic, Water Repellent, UV Protection",
    "clicks": 2,
    "impressions": 83,
    "revenue": 0.0,
    "cost": 0.87
  },
  "shopify_gb_8784876241170_47735017013522": {
    "product_id": "shopify_gb_8784876241170_47735017013522",
    "product_title": "Wax Polish - Antique Brown 300ml | Natural Beeswax & Carnauba Furniture Polish | Non-Toxic & Water Repellent",
    "clicks": 0,
    "impressions": 14,
    "revenue": 0.0,
    "cost": 0.0
  },
  "shopify_gb_8784876241170_47735017046290": {
    "product_id": "shopify_gb_8784876241170_47735017046290",
    "product_title": "Wax Polish 600ml - Antique Brown | Natural Beeswax & Carnauba Furniture Polish | Non-Toxic & Water Repellent",
    "clicks": 0,
    "impressions": 58,
    "revenue": 0.0,
    "cost": 0.0
  },
  "shopify_gb_8784876372242_47096882004242": {
    "product_id": "shopify_gb_8784876372242_47096882004242",
    "product_title": "Epoxy Wood Repair Stick 7 Inch | Wood Repair, Rebuild, Re-Paint",
    "clicks": 0,
    "impressions": 44,
    "revenue": 0.0,
    "cost": 0.0
  },
  "shopify_gb_8784876470546_47734824108306": {
    "product_id": "shopify_gb_8784876470546_47734824108306",
    "product_title": "Danish Oil | Enhances Natural Beauty Of Wooden Surfaces 500ml",
    "clicks": 1,
    "impressions": 37,
    "revenue": 0.0,
    "cost": 0.17
  },
  "shopify_gb_8784876470546_47734824141074": {
    "product_id": "shopify_gb_8784876470546_47734824141074",
    "product_title": "Danish Oil 1 Litre | Enhances Natural Beauty Of Wooden Surfaces",
    "clicks": 3,
    "impressions": 152,
    "revenue": 0.0,
    "cost": 1.82
  },
  "shopify_gb_8784876470546_47734824173842": {
    "product_id": "shopify_gb_8784876470546_47734824173842",
    "product_title": "Grain Guard Danish Oil 5 Litre - Enhances Natural Beauty of Wooden Surfaces-Water Repellent-Interior/Exterior Use- 6-10m\u00b2 Coverage-Natural Finish",
    "clicks": 0,
    "impressions": 71,
    "revenue": 0.0,
    "cost": 0.0
  },
  "shopify_gb_8784876896530_47734926967058": {
    "product_id": "shopify_gb_8784876896530_47734926967058",
    "product_title": "Wax Filler Repair Sticks | Furniture Repair Kit | Multi-Surface: Wood, Plastic, Hard Surfaces | 4x40mm - Dark Wood",
    "clicks": 0,
    "impressions": 65,
    "revenue": 0.0,
    "cost": 0.0
  },
  "shopify_gb_8784876896530_47734926999826": {
    "product_id": "shopify_gb_8784876896530_47734926999826",
    "product_title": "Wax Filler Wood Repair Sticks 4 x 40mm - Light Wood - Furniture Repair Kit | Multi-Surface: Wood, Plastic, Hard Surfaces",
    "clicks": 0,
    "impressions": 27,
    "revenue": 0.0,
    "cost": 0.0
  },
  "shopify_gb_8784876896530_47734927032594": {
    "product_id": "shopify_gb_8784876896530_47734927032594",
    "product_title": "Grain Guard Wax Filler Wood Repair Sticks - 4x40mm - Quick Fix - DarkWood/MediumWood/LightWood - Instant Repair",
    "clicks": 4,
    "impressions": 342,
    "revenue": 0.0,
    "cost": 0.88
  },
  "shopify_gb_8784876896530_47734927065362": {
    "product_id": "shopify_gb_8784876896530_47734927065362",
    "product_title": "Wax Filler Wood Repair Sticks 4x40mm - White Wood | Furniture Repair Kit | Multi-Surface: Wood, Plastic, Hard Surfaces",
    "clicks": 0,
    "impressions": 89,
    "revenue": 0.0,
    "cost": 0.0
  },
  "shopify_gb_8784876896530_47734927098130": {
    "product_id": "shopify_gb_8784876896530_47734927098130",
    "product_title": "Grain Guard Wax Filler Sticks: 4x40mm - Quick Fix, Multi-Surface Repair Kit for Wood, Laminate & Plastic",
    "clicks": 1,
    "impressions": 81,
    "revenue": 0.0,
    "cost": 0.23
  },
  "shopify_gb_8784877551890_47734888530194": {
    "product_id": "shopify_gb_8784877551890_47734888530194",
    "product_title": "Touch-Up & Scratch Repair Pen -10ml - Agate Grey | (RAL 7038) | Multi-Surface Wood, UPVC, Metal | Furniture, Worktops, Doors & Windows",
    "clicks": 0,
    "impressions": 14,
    "revenue": 0.0,
    "cost": 0.0
  },
  "shopify_gb_8784877551890_47734888562962": {
    "product_id": "shopify_gb_8784877551890_47734888562962",
    "product_title": "Touch-Up & Scratch Repair Pen 10ml - Anthracite Grey Gloss (RAL 7016) | Multi-Surface Wood, UPVC, Metal | Furniture, Worktops, Doors & Windows",
    "clicks": 0,
    "impressions": 14,
    "revenue": 0.0,
    "cost": 0.0
  },
  "shopify_gb_8784877551890_47734888595730": {
    "product_id": "shopify_gb_8784877551890_47734888595730",
    "product_title": "Touch-Up & Scratch Repair Pens | Multi-Surface Wood, UPVC, Metal | Furniture, Worktops, Doors & Windows | 10ml - Anthracite Grey MATT (RAL 7016)",
    "clicks": 0,
    "impressions": 27,
    "revenue": 0.0,
    "cost": 0.0
  },
  "shopify_gb_8784877551890_47734888628498": {
    "product_id": "shopify_gb_8784877551890_47734888628498",
    "product_title": "Touch-Up & Scratch Repair Pen 10ml - Cream (RAL 9001) | Multi-Surface Wood, UPVC, Metal | Furniture, Worktops, Doors & Windows",
    "clicks": 0,
    "impressions": 57,
    "revenue": 0.0,
    "cost": 0.0
  },
  "shopify_gb_8784877551890_47734888661266": {
    "product_id": "shopify_gb_8784877551890_47734888661266",
    "product_title": "Touch-Up & Scratch Repair Pen 10ml - Jet Black (RAL 9005) | Multi-Surface Wood, UPVC, Metal | Furniture, Worktops, Doors & Windows",
    "clicks": 0,
    "impressions": 28,
    "revenue": 0.0,
    "cost": 0.0
  },
  "shopify_gb_8784877551890_47734888694034": {
    "product_id": "shopify_gb_8784877551890_47734888694034",
    "product_title": "Touch-Up & Scratch Repair Pen 10ml - Light Grey (RAL 7035) | Multi-Surface Wood, UPVC, Metal | Furniture, Worktops, Doors & Windows",
    "clicks": 0,
    "impressions": 11,
    "revenue": 0.0,
    "cost": 0.0
  },
  "shopify_gb_8784877551890_47734888726802": {
    "product_id": "shopify_gb_8784877551890_47734888726802",
    "product_title": "Touch-Up & Scratch Repair Pen - 10ml - Pure White (RAL 9010) | Multi-Surface Wood, UPVC, Metal | Furniture, Worktops, Doors & Windows",
    "clicks": 0,
    "impressions": 20,
    "revenue": 0.0,
    "cost": 0.0
  },
  "shopify_gb_8784877551890_47734888759570": {
    "product_id": "shopify_gb_8784877551890_47734888759570",
    "product_title": "Touch-Up & Scratch Repair Pen 10ml - Signal White (RAL 9003) | Multi-Surface Wood, UPVC, Metal | Furniture, Worktops, Doors & Windows",
    "clicks": 0,
    "impressions": 10,
    "revenue": 0.0,
    "cost": 0.0
  },
  "shopify_gb_8784877551890_47734888792338": {
    "product_id": "shopify_gb_8784877551890_47734888792338",
    "product_title": "Touch-Up & Scratch Repair Pen 10ml - Slate Grey (RAL 7015) | Multi-Surface Wood, UPVC, Metal | Furniture, Worktops, Doors & Windows",
    "clicks": 0,
    "impressions": 14,
    "revenue": 0.0,
    "cost": 0.0
  },
  "shopify_gb_8784877551890_47734888825106": {
    "product_id": "shopify_gb_8784877551890_47734888825106",
    "product_title": "Touch-Up & Scratch Repair Pen - Traffic White 10ml | Multi-Surface Wood, UPVC, Metal | Furniture, Worktops, Doors & Windows (RAL 9016)",
    "clicks": 0,
    "impressions": 37,
    "revenue": 0.0,
    "cost": 0.0
  },
  "shopify_gb_8784877551890_48957996106002": {
    "product_id": "shopify_gb_8784877551890_48957996106002",
    "product_title": "Touch-Up & Scratch Repair Pen 10ml - Pebble Grey (RAL 7032) | Multi-Surface Wood, UPVC, Metal",
    "clicks": 0,
    "impressions": 7,
    "revenue": 0.0,
    "cost": 0.0
  },
  "shopify_gb_8784877551890_48957996138770": {
    "product_id": "shopify_gb_8784877551890_48957996138770",
    "product_title": "Touch-Up & Scratch Repair Pen 10ml - Basalt Grey (RAL 7012) | Multi-Surface Wood, UPVC, Metal | Furniture, Worktops, Doors & Windows",
    "clicks": 0,
    "impressions": 7,
    "revenue": 0.0,
    "cost": 0.0
  },
  "shopify_gb_8784877551890_48957996171538": {
    "product_id": "shopify_gb_8784877551890_48957996171538",
    "product_title": "Touch-Up & Scratch Repair Pen -10ml - Light Ivory (RAL 1015) | Multi-Surface Wood, UPVC, Metal | Furniture, Worktops, Doors & Windows",
    "clicks": 0,
    "impressions": 6,
    "revenue": 0.0,
    "cost": 0.0
  },
  "shopify_gb_8784877551890_48957996204306": {
    "product_id": "shopify_gb_8784877551890_48957996204306",
    "product_title": "Touch-Up & Scratch Repair Pens | Multi-Surface Wood, UPVC, Metal | Furniture, Worktops, Doors & Windows | 10ml - Black Brown (RAL 8022)",
    "clicks": 0,
    "impressions": 18,
    "revenue": 0.0,
    "cost": 0.0
  },
  "shopify_gb_8784877748498_47734979723538": {
    "product_id": "shopify_gb_8784877748498_47734979723538",
    "product_title": "Grain Guard Water-Based Aerosol Wood Stain - 400ml Black Ebony - Quick Dry, Long Lasting, Easy Application - For All Woods - Premium Finish",
    "clicks": 0,
    "impressions": 11,
    "revenue": 0.0,
    "cost": 0.0
  },
  "shopify_gb_8784877748498_47734979756306": {
    "product_id": "shopify_gb_8784877748498_47734979756306",
    "product_title": "Water Based Wood Stain Aerosol - 2 x 400ml - Black Ebony",
    "clicks": 0,
    "impressions": 12,
    "revenue": 0.0,
    "cost": 0.0
  },
  "shopify_gb_8784877748498_47734979789074": {
    "product_id": "shopify_gb_8784877748498_47734979789074",
    "product_title": "Wood Stain Aerosol | Water Based Aerosol Stain | 400ml Three Pack - Black Ebony",
    "clicks": 0,
    "impressions": 11,
    "revenue": 0.0,
    "cost": 0.0
  },
  "shopify_gb_8784877748498_47734979821842": {
    "product_id": "shopify_gb_8784877748498_47734979821842",
    "product_title": "Water Based Aerosol Wood Stain | 400ml - Dark Red Mahogany - Quick Drying For A Premium Finish",
    "clicks": 0,
    "impressions": 13,
    "revenue": 0.0,
    "cost": 0.0
  },
  "shopify_gb_8784877748498_47734979854610": {
    "product_id": "shopify_gb_8784877748498_47734979854610",
    "product_title": "Wood Stain Aerosol 2 x 400ml - Dark Red Mahogany | Water Based Aerosol Stain",
    "clicks": 0,
    "impressions": 6,
    "revenue": 0.0,
    "cost": 0.0
  },
  "shopify_gb_8784877748498_47734979887378": {
    "product_id": "shopify_gb_8784877748498_47734979887378",
    "product_title": "Water Based Aerosol Wood Stain - Dark Red Mahogany - 400ml Three Pack - Dark Red Mahogany",
    "clicks": 0,
    "impressions": 1,
    "revenue": 0.0,
    "cost": 0.0
  },
  "shopify_gb_8784877748498_47734979920146": {
    "product_id": "shopify_gb_8784877748498_47734979920146",
    "product_title": "Water Based Wood Stain Aerosol 400ml - English Oak",
    "clicks": 0,
    "impressions": 6,
    "revenue": 0.0,
    "cost": 0.0
  },
  "shopify_gb_8784877748498_47734979952914": {
    "product_id": "shopify_gb_8784877748498_47734979952914",
    "product_title": "Wood Stain Aerosol - Water Based - 2 x 400ml - English Oak - Fade Resistant - Quick Dry",
    "clicks": 0,
    "impressions": 2,
    "revenue": 0.0,
    "cost": 0.0
  },
  "shopify_gb_8784877748498_47734979985682": {
    "product_id": "shopify_gb_8784877748498_47734979985682",
    "product_title": "3 x 400ml Wood Stain Aerosol - English Oak - Water Based",
    "clicks": 0,
    "impressions": 15,
    "revenue": 0.0,
    "cost": 0.0
  },
  "shopify_gb_8784877748498_47734980018450": {
    "product_id": "shopify_gb_8784877748498_47734980018450",
    "product_title": "Light Oak Water Based Wood Stain Aerosol 400ml - Qucik Dry - Premium Finish",
    "clicks": 1,
    "impressions": 41,
    "revenue": 0.0,
    "cost": 0.22
  },
  "shopify_gb_8784877748498_47734980051218": {
    "product_id": "shopify_gb_8784877748498_47734980051218",
    "product_title": "Water Based Wood Aerosol Stain | 400ml Two Pack - Light Oak",
    "clicks": 0,
    "impressions": 2,
    "revenue": 0.0,
    "cost": 0.0
  },
  "shopify_gb_8784877748498_47734980083986": {
    "product_id": "shopify_gb_8784877748498_47734980083986",
    "product_title": "Water Based Aerosol Stain | 3 x 400ml - Light Oak",
    "clicks": 0,
    "impressions": 15,
    "revenue": 0.0,
    "cost": 0.0
  },
  "shopify_gb_8784877748498_47734980116754": {
    "product_id": "shopify_gb_8784877748498_47734980116754",
    "product_title": "Wood Stain Aerosol | Water Based Aerosol Stain | 400ml - Medium Oak",
    "clicks": 1,
    "impressions": 39,
    "revenue": 0.0,
    "cost": 0.14
  },
  "shopify_gb_8784877748498_47734980149522": {
    "product_id": "shopify_gb_8784877748498_47734980149522",
    "product_title": "Water Based Aerosol Wood Stain - 2 x 400ml - Medium Oak",
    "clicks": 0,
    "impressions": 2,
    "revenue": 0.0,
    "cost": 0.0
  },
  "shopify_gb_8784877748498_47734980182290": {
    "product_id": "shopify_gb_8784877748498_47734980182290",
    "product_title": "Grain Guard Wood Stain Aerosol (3x400ml) - Medium Oak, Quick Dry, Premium",
    "clicks": 0,
    "impressions": 5,
    "revenue": 0.0,
    "cost": 0.0
  },
  "shopify_gb_9397473673490_48957607149842": {
    "product_id": "shopify_gb_9397473673490_48957607149842",
    "product_title": "Wood Stain Touch-Up Marker Pens | Various Colours | Touching Up & Staining Scratches, Scuffs, Marks & Dents | Ideal For Wooden Floors, Furniture,",
    "clicks": 0,
    "impressions": 1,
    "revenue": 0.0,
    "cost": 0.0
  },
  "shopify_gb_9397473673490_48957607182610": {
    "product_id": "shopify_gb_9397473673490_48957607182610",
    "product_title": "Wood Stain Touch-Up Marker Pens | Various Colours | Touching Up & Staining Scratches, Scuffs, Marks & Dents | Ideal For Wooden Floors, Furniture,",
    "clicks": 0,
    "impressions": 13,
    "revenue": 0.0,
    "cost": 0.0
  },
  "shopify_gb_9397473673490_48957607215378": {
    "product_id": "shopify_gb_9397473673490_48957607215378",
    "product_title": "Wood Stain Touch-Up Marker Pen 10ml - Golden Oak | Touching Up & Staining Scratches, Scuffs, Marks & Dents | Ideal For Wooden Floors, Furniture",
    "clicks": 1,
    "impressions": 42,
    "revenue": 0.0,
    "cost": 0.37
  },
  "shopify_gb_9397473673490_48957607248146": {
    "product_id": "shopify_gb_9397473673490_48957607248146",
    "product_title": "Wood Stain Touch-Up Marker Pens | Various Colours | Touching Up & Staining Scratches, Scuffs, Marks & Dents | Ideal For Wooden Floors, Furniture,",
    "clicks": 0,
    "impressions": 2,
    "revenue": 0.0,
    "cost": 0.0
  },
  "shopify_gb_9397473673490_48957607280914": {
    "product_id": "shopify_gb_9397473673490_48957607280914",
    "product_title": "Wood Stain Touch-Up Marker Pen - French Oak | Touching Up & Staining Scratches, Scuffs, Marks & Dents | Ideal For Wooden Floors & Furniture",
    "clicks": 0,
    "impressions": 57,
    "revenue": 0.0,
    "cost": 0.0
  },
  "shopify_gb_9397473673490_48957607313682": {
    "product_id": "shopify_gb_9397473673490_48957607313682",
    "product_title": "Darjk Pine Wood Stain Touch-Up Marker Pens For Touching Up & Staining Scratches, Scuffs, Marks & Dents | Fast Drying Formula",
    "clicks": 0,
    "impressions": 1,
    "revenue": 0.0,
    "cost": 0.0
  },
  "shopify_gb_9397473673490_48957607346450": {
    "product_id": "shopify_gb_9397473673490_48957607346450",
    "product_title": "Wood Stain Touch-Up Marker Pens - Antique Stripped Pine | Touching Up & Staining Scratches, Scuffs, Marks & Dents | For Wooden Floors & Furniture",
    "clicks": 0,
    "impressions": 4,
    "revenue": 0.0,
    "cost": 0.0
  },
  "shopify_gb_9397473673490_48957607379218": {
    "product_id": "shopify_gb_9397473673490_48957607379218",
    "product_title": "Wood Stain Touch-Up Marker Pens | Various Colours | Touching Up & Staining Scratches, Scuffs, Marks & Dents | Ideal For Wooden Floors, Furniture,",
    "clicks": 0,
    "impressions": 1,
    "revenue": 0.0,
    "cost": 0.0
  },
  "shopify_gb_9397473673490_48957607411986": {
    "product_id": "shopify_gb_9397473673490_48957607411986",
    "product_title": "Wood Stain Touch-Up Marker Pens | Touching Up & Staining Scratches, Scuffs, Marks & Dents | Ideal For Wooden Floors, Furniture,",
    "clicks": 0,
    "impressions": 3,
    "revenue": 0.0,
    "cost": 0.0
  },
  "shopify_gb_9397473673490_48957607444754": {
    "product_id": "shopify_gb_9397473673490_48957607444754",
    "product_title": "Wood Stain Touch-Up Marker Pens | Various Colours | Touching Up & Staining Scratches, Scuffs, Marks & Dents | Ideal For Wooden Floors, Furniture,",
    "clicks": 0,
    "impressions": 2,
    "revenue": 0.0,
    "cost": 0.0
  },
  "shopify_gb_9397473673490_48957607477522": {
    "product_id": "shopify_gb_9397473673490_48957607477522",
    "product_title": "Wood Stain Touch-Up Marker Pens | Various Colours | Touching Up & Staining Scratches, Scuffs, Marks & Dents | Ideal For Wooden Floors, Furniture,",
    "clicks": 0,
    "impressions": 1,
    "revenue": 0.0,
    "cost": 0.0
  },
  "shopify_gb_9397473673490_48957607510290": {
    "product_id": "shopify_gb_9397473673490_48957607510290",
    "product_title": "Dark Walnut Wood Stain Touch-Up Marker Pen | Touching Up & Staining Scratches, Scuffs, Marks & Dents | Ideal For Wooden Floors, Furniture,",
    "clicks": 0,
    "impressions": 52,
    "revenue": 0.0,
    "cost": 0.0
  },
  "shopify_gb_9398059630866_48958143103250": {
    "product_id": "shopify_gb_9398059630866_48958143103250",
    "product_title": "Grain Guard Hardwood Colour Restorer Aerosol - Revives, Protects Wood - Water Repellent, UV Protection, Brown 500ml",
    "clicks": 0,
    "impressions": 13,
    "revenue": 0.0,
    "cost": 0.0
  },
  "shopify_gb_9398059630866_48958143136018": {
    "product_id": "shopify_gb_9398059630866_48958143136018",
    "product_title": "Hardwood Colour Restorer Aerosol 2 X 500ml - Clean, Restore, Protect | Revivies & Renews Faded And Greying Wood - Water Repellent",
    "clicks": 1,
    "impressions": 105,
    "revenue": 0.0,
    "cost": 0.38
  },
  "shopify_gb_9398059630866_48958143168786": {
    "product_id": "shopify_gb_9398059630866_48958143168786",
    "product_title": "Hardwood Colour Restorer Aerosol 3 X 500ml | Clean, Restore, Protect | Revivies & Renews Faded And Greying Wood | Water Repellent",
    "clicks": 1,
    "impressions": 65,
    "revenue": 0.0,
    "cost": 0.5
  },
  "shopify_gb_9715210879250_50003891323154": {
    "product_id": "shopify_gb_9715210879250_50003891323154",
    "product_title": "Grain Guard Chopping Board Oil 500ml - Food Grade Mineral Oil; Odourless, Tasteless - Protects & Enhances;",
    "clicks": 1,
    "impressions": 202,
    "revenue": 0.0,
    "cost": 0.25
  },
  "shopify_gb_9715210879250_50003891355922": {
    "product_id": "shopify_gb_9715210879250_50003891355922",
    "product_title": "Chopping Board Oil 1 Litre - Food Grade Mineral Oil Odourless & Tasteless",
    "clicks": 0,
    "impressions": 177,
    "revenue": 0.0,
    "cost": 0.0
  },
  "shopify_gb_9715262783762_50004105298194": {
    "product_id": "shopify_gb_9715262783762_50004105298194",
    "product_title": "Sealing Oil For Wooden Garden Furniture & Decking 500ml | Protects Wood Against Weather & UV",
    "clicks": 0,
    "impressions": 87,
    "revenue": 0.0,
    "cost": 0.0
  },
  "shopify_gb_9715262783762_50004105330962": {
    "product_id": "shopify_gb_9715262783762_50004105330962",
    "product_title": "Sealing Oil For Wood | Protects Wood Against Weather & UV | For Garden Furniture & Decking 1 Litre",
    "clicks": 0,
    "impressions": 8,
    "revenue": 0.0,
    "cost": 0.0
  },
  "shopify_gb_9715262783762_50004105363730": {
    "product_id": "shopify_gb_9715262783762_50004105363730",
    "product_title": "Sealing Oil For Wood 5 Litre | Protects Wood Against Weather & UV | For Garden Furniture & Decking",
    "clicks": 0,
    "impressions": 8,
    "revenue": 0.0,
    "cost": 0.0
  }
}